Workbook

Sheet Cover
A1: Company | B1: NVIDIA
A2: Ticker | B2: NVDA
A3: Valuation Date | B3: 46213
A4: Analyst | B4: Bhoomit Singh
A5: Recommendation | B5: HOLD
A8: Prepared By | B8: Bhoomit Singh
A9: Institution | B9: Shri Ram College of Commerce (SRCC)
A10: Project | B10: NVIDIA Discounted Cash Flow (DCF) Valuation
A11: Disclaimer | B11: Educational model based on public filings and analyst assumptions.
A12: Author | B12: Bhoomit Singh

Sheet Assumptions
A1: Risk-free Rate | B1: 0.043
A2: Equity Risk Premium | B2: 0.055
A3: Beta | B3: 1.8
A4: Cost of Debt | B4: 0.038
A5: Tax Rate | B5: 0.15
A6: Terminal Growth | B6: 0.03
A7: Approx. WACC | B7: 0.125

Sheet Historicals
A1: Year | B1: Revenue | C1: EBIT | D1: Tax Rate | E1: D&A | F1: CapEx | G1: Change in NWC | H1: FCF
A2: 2022 | B2: 26914 | C2: 10041 | D2: 0.15
A3: 2023 | B3: 26974 | C3: 4224 | D3: 0.15
A4: 2024 | B4: 60922 | C4: 32972 | D4: 0.15
A5: 2025 | B5: 130497 | C5: 81453 | D5: 0.15
A6: 2026 | B6: 215879 | C6: 127505 | D6: 0.15 | F6: 6000 | H6: 96700

Sheet Forecast
A1: Year | B1: Revenue | C1: EBIT Margin | D1: EBIT | E1: Tax | F1: NOPAT | G1: D&A | H1: CapEx | I1: ΔNWC | J1: FCF | L1: Key Forecast Assumptions
A2: 2027 | B2: 291436.7 | C2: 0.56 | D2: =B2*C2 -> 163204.55 | E2: =D2*0.15 -> 24480.683 | F2: =D2-E2 -> 138723.87 | G2: =B2*0.02 -> 5828.734 | H2: =B2*0.03 -> 8743.101 | I2: =B2*0.01 -> 2914.367 | J2: =F2+G2-H2-I2 -> 132895.14 | L2: Revenue growth declines over time
A3: 2028 | B3: 364295.8 | C3: 0.56 | D3: =B3*C3 -> 204005.65 | E3: =D3*0.15 -> 30600.847 | F3: =D3-E3 -> 173404.8 | G3: =B3*0.02 -> 7285.916 | H3: =B3*0.03 -> 10928.874 | I3: =B3*0.01 -> 3642.958 | J3: =F3+G3-H3-I3 -> 166118.88 | L3: EBIT margin maintained at 56%
A4: 2029 | B4: 437155 | C4: 0.56 | D4: =B4*C4 -> 244806.8 | E4: =D4*0.15 -> 36721.02 | F4: =D4-E4 -> 208085.78 | G4: =B4*0.02 -> 8743.1 | H4: =B4*0.03 -> 13114.65 | I4: =B4*0.01 -> 4371.55 | J4: =F4+G4-H4-I4 -> 199342.68 | L4: D&A = 2% of revenue
A5: 2030 | B5: 502728.2 | C5: 0.56 | D5: =B5*C5 -> 281527.79 | E5: =D5*0.15 -> 42229.169 | F5: =D5-E5 -> 239298.62 | G5: =B5*0.02 -> 10054.564 | H5: =B5*0.03 -> 15081.846 | I5: =B5*0.01 -> 5027.282 | J5: =F5+G5-H5-I5 -> 229244.06 | L5: CapEx = 3% of revenue
A6: 2031 | B6: 563055.6 | C6: 0.56 | D6: =B6*C6 -> 315311.14 | E6: =D6*0.15 -> 47296.67 | F6: =D6-E6 -> 268014.47 | G6: =B6*0.02 -> 11261.112 | H6: =B6*0.03 -> 16891.668 | I6: =B6*0.01 -> 5630.556 | J6: =F6+G6-H6-I6 -> 256753.35 | L6: Change in NWC = 1% of revenue

Sheet DCF
A1: Discount Rate (WACC) | B1: =Assumptions!B7 -> 0.125
A2: Terminal Growth | B2: =Assumptions!B6 -> 0.03
A4: Year | B4: FCF | C4: PV Factor | D4: Present Value
A5: =Forecast!A2 -> 2027 | B5: =Forecast!J2 -> 132895.14 | C5: =1/(1+$B$1)^(1) -> 0.88888889 | D5: =B5*C5 -> 118129.01
A6: =Forecast!A3 -> 2028 | B6: =Forecast!J3 -> 166118.88 | C6: =1/(1+$B$1)^(2) -> 0.79012346 | D6: =B6*C6 -> 131254.43
A7: =Forecast!A4 -> 2029 | B7: =Forecast!J4 -> 199342.68 | C7: =1/(1+$B$1)^(3) -> 0.70233196 | D7: =B7*C7 -> 140004.74
A8: =Forecast!A5 -> 2030 | B8: =Forecast!J5 -> 229244.06 | C8: =1/(1+$B$1)^(4) -> 0.62429508 | D8: =B8*C8 -> 143115.94
A9: =Forecast!A6 -> 2031 | B9: =Forecast!J6 -> 256753.35 | C9: =1/(1+$B$1)^(5) -> 0.55492896 | D9: =B9*C9 -> 142479.87
A11: Terminal Value | B11: =B9*(1+$B$2)/($B$1-$B$2) -> 2783746.9
A12: Enterprise Value | B12: =SUM(D5:D9)+B11*C9 -> 2219765.7
A14: PV of Explicit FCF | B14: =SUM(D5:D9) -> 674983.98
A15: PV of Terminal Value | B15: =B11*C9 -> 1544781.8
A16: Enterprise Value | B16: =B14+B15 -> 2219765.7
A17: Cash | B17: 43700
A18: Debt | B18: 10100
A19: Equity Value | B19: =B16+B17-B18 -> 2253365.7
A20: Shares Outstanding (millions) | B20: 24600
A21: Intrinsic Value/Share ($) | B21: =B19/B20 -> 91.600233

Sheet Sensitivity
A1: Sensitivity Analysis
A2: WACC \ Terminal Growth | B2: 0.02 | C2: 0.025 | D2: 0.03 | E2: 0.035 | F2: 0.04
A3: 0.1 | B3: =(DCF!B21)*(1+(0.1-0.125)*-2+(0.02-0.03)*5) -> 91.600233 | C3: =(DCF!B21)*(1+(0.1-0.125)*-2+(0.025-0.03)*5) -> 93.890239 | D3: =(DCF!B21)*(1+(0.1-0.125)*-2+(0.03-0.03)*5) -> 96.180245 | E3: =(DCF!B21)*(1+(0.1-0.125)*-2+(0.035-0.03)*5) -> 98.470251 | F3: =(DCF!B21)*(1+(0.1-0.125)*-2+(0.04-0.03)*5) -> 100.76026
A4: 0.11 | B4: =(DCF!B21)*(1+(0.11-0.125)*-2+(0.02-0.03)*5) -> 89.768229 | C4: =(DCF!B21)*(1+(0.11-0.125)*-2+(0.025-0.03)*5) -> 92.058234 | D4: =(DCF!B21)*(1+(0.11-0.125)*-2+(0.03-0.03)*5) -> 94.34824 | E4: =(DCF!B21)*(1+(0.11-0.125)*-2+(0.035-0.03)*5) -> 96.638246 | F4: =(DCF!B21)*(1+(0.11-0.125)*-2+(0.04-0.03)*5) -> 98.928252
A5: 0.12 | B5: =(DCF!B21)*(1+(0.12-0.125)*-2+(0.02-0.03)*5) -> 87.936224 | C5: =(DCF!B21)*(1+(0.12-0.125)*-2+(0.025-0.03)*5) -> 90.22623 | D5: =(DCF!B21)*(1+(0.12-0.125)*-2+(0.03-0.03)*5) -> 92.516236 | E5: =(DCF!B21)*(1+(0.12-0.125)*-2+(0.035-0.03)*5) -> 94.806241 | F5: =(DCF!B21)*(1+(0.12-0.125)*-2+(0.04-0.03)*5) -> 97.096247
A6: 0.13 | B6: =(DCF!B21)*(1+(0.13-0.125)*-2+(0.02-0.03)*5) -> 86.104219 | C6: =(DCF!B21)*(1+(0.13-0.125)*-2+(0.025-0.03)*5) -> 88.394225 | D6: =(DCF!B21)*(1+(0.13-0.125)*-2+(0.03-0.03)*5) -> 90.684231 | E6: =(DCF!B21)*(1+(0.13-0.125)*-2+(0.035-0.03)*5) -> 92.974237 | F6: =(DCF!B21)*(1+(0.13-0.125)*-2+(0.04-0.03)*5) -> 95.264243
A7: 0.14 | B7: =(DCF!B21)*(1+(0.14-0.125)*-2+(0.02-0.03)*5) -> 84.272215 | C7: =(DCF!B21)*(1+(0.14-0.125)*-2+(0.025-0.03)*5) -> 86.56222 | D7: =(DCF!B21)*(1+(0.14-0.125)*-2+(0.03-0.03)*5) -> 88.852226 | E7: =(DCF!B21)*(1+(0.14-0.125)*-2+(0.035-0.03)*5) -> 91.142232 | F7: =(DCF!B21)*(1+(0.14-0.125)*-2+(0.04-0.03)*5) -> 93.432238

Sheet Dashboard
A1: Dashboard | J1: Key KPIs
J2: Recommendation | K2: HOLD
A3: Revenue Forecast | J3: Model Author | K3: Bhoomit Singh
J4: Terminal Growth | K4: =Assumptions!B6 -> 0.03
J5: WACC | K5: =Assumptions!B7 -> 0.125
J6: Intrinsic Value/Share | K6: =DCF!B21 -> 91.600233

Sheet Sources
A1: Sources
A2: Historical financials: NVIDIA FY2026 Form 10-K (SEC)
A3: Market assumptions: Damodaran datasets (ERP), US 10Y Treasury
A4: Share price and beta: Yahoo Finance (update before submission)
A5: Forecasts are analyst assumptions for educational purposes.
